notbadai_tools_chat/__init__.py
notbadai_tools_chat/tools.system.md
notbadai_tools_chat/common/__init__.py
notbadai_tools_chat/common/diff.py
notbadai_tools_chat/common/file_type.py
notbadai_tools_chat/common/formatting.py
notbadai_tools_chat/common/git_client.py
notbadai_tools_chat/common/llm.py
notbadai_tools_chat/common/models.py
notbadai_tools_chat/common/prompt.py
notbadai_tools_chat/common/settings.py
notbadai_tools_chat/common/terminal.py
notbadai_tools_chat/common/utils.py
notbadai_tools_chat/utils/__init__.py
notbadai_tools_chat/utils/llm.py
notbadai_tools_chat-0.1.5.dist-info/METADATA
notbadai_tools_chat-0.1.5.dist-info/WHEEL
notbadai_tools_chat-0.1.5.dist-info/top_level.txt
notbadai_tools_chat-0.1.5.dist-info/RECORD
